s3webcache/__init__.py
tests/__init__.py
tests/test_s3webcache.py
S3WebCache-0.1.7.dist-info/LICENSE.txt
S3WebCache-0.1.7.dist-info/METADATA
S3WebCache-0.1.7.dist-info/WHEEL
S3WebCache-0.1.7.dist-info/top_level.txt
S3WebCache-0.1.7.dist-info/RECORD
