Metadata-Version: 2.1
Name: S3WebCache
Version: 0.1.7
Summary: UNKNOWN
Home-page: UNKNOWN
Author-email: dhking@wharton.upenn.edu
License: MIT
Platform: UNKNOWN
Requires-Dist: requests
Requires-Dist: boto3
